e621_dl.py
e621_dl-2.2.5.dist-info/entry_points.txt
e621_dl-2.2.5.dist-info/WHEEL
e621_dl-2.2.5.dist-info/METADATA
e621_dl-2.2.5.dist-info/RECORD
