Metadata-Version: 2.1
Name: e621-dl
Version: 2.2.5
Summary: A simple and fast e621 post/pool downloader
Home-page: https://github.com/hmiku8338/e621-dl
License: MIT
Keywords: furry,yiff,e621,api,booru,downloader
Author: HMiku8338
Author-email: hmiku8338@gmail.com
Requires-Python: >=3.7,<4.0
Classifier: License :: OSI Approved :: MIT License
Classifier: Programming Language :: Python :: 3
Classifier: Programming Language :: Python :: 3.10
Classifier: Programming Language :: Python :: 3.7
Classifier: Programming Language :: Python :: 3.8
Classifier: Programming Language :: Python :: 3.9
Requires-Dist: e621-stable (>=1.0.2,<2.0.0)
Requires-Dist: requests (>=2.27.1,<3.0.0)
Requires-Dist: tqdm (>=4.64.0,<5.0.0)
Requires-Dist: typer[all] (>=0.7.0,<0.8.0)
Project-URL: Repository, https://github.com/hmiku8338/e621-dl
